pytoolconfig/__init__.py
pytoolconfig/_version.py
pytoolconfig/documentation.py
pytoolconfig/fields.py
pytoolconfig/py.typed
pytoolconfig/pytoolconfig.py
pytoolconfig/sources/__init__.py
pytoolconfig/sources/ini.py
pytoolconfig/sources/pyproject.py
pytoolconfig/sources/pytool.py
pytoolconfig/sources/setup_cfg.py
pytoolconfig/sources/source.py
pytoolconfig/types.py
pytoolconfig/universal_config.py
pytoolconfig/utils.py
pytoolconfig-1.2.5.dist-info/WHEEL
pytoolconfig-1.2.5.dist-info/METADATA
pytoolconfig-1.2.5.dist-info/licenses/LICENSE
pytoolconfig-1.2.5.dist-info/RECORD
