Metadata-Version: 2.1
Name: pytoolconfig
Version: 1.2.5
Summary: Python tool configuration
Author-email: bageljr <bageljr897@protonmail.com>
Requires-Python: >=3.7
Provides-Extra: doc
Provides-Extra: gendocs
Provides-Extra: global
Provides-Extra: validation
Project-URL: Homepage, https://github.com/bageljrkhanofemus/pytoolconfig
